consul_docker_autosync/__init__.py
consul_docker_autosync/autosync.py
consul_docker_autosync/cli.py
consul_docker_autosync/http_server.py
consul_docker_autosync-0.1.0.dist-info/entry_points.txt
consul_docker_autosync-0.1.0.dist-info/WHEEL
consul_docker_autosync-0.1.0.dist-info/METADATA
consul_docker_autosync-0.1.0.dist-info/RECORD
