Metadata-Version: 2.1
Name: consul-docker-autosync
Version: 0.1.0
Summary: 
Author: Dani Hodovic
Author-email: dani.hodovic@gmail.com
Requires-Python: >=3.8,<4.0
Classifier: Programming Language :: Python :: 3
Classifier: Programming Language :: Python :: 3.8
Classifier: Programming Language :: Python :: 3.9
Requires-Dist: Flask (>=1.1.2,<2.0.0)
Requires-Dist: click (>=7.1.2,<8.0.0)
Requires-Dist: docker (>=5.0.0,<6.0.0)
Requires-Dist: loguru (>=0.5.3,<0.6.0)
Requires-Dist: python-consul2 (>=0.1.5,<0.2.0)
Requires-Dist: waitress (>=2.0.0,<3.0.0)
